topgg/__init__.py
topgg/client.py
topgg/errors.py
topgg/http.py
topgg/py.typed
topgg/ratelimiter.py
topgg/types.py
topgg/webhook.py
topggpy-1.4.0.dist-info/LICENSE
topggpy-1.4.0.dist-info/METADATA
topggpy-1.4.0.dist-info/WHEEL
topggpy-1.4.0.dist-info/top_level.txt
topggpy-1.4.0.dist-info/RECORD
