Metadata-Version: 2.1
Name: topggpy
Version: 1.4.0
Summary: A simple API wrapper for Top.gg written in Python.
Home-page: https://github.com/top-gg/python-sdk
Author: Assanali Mukhanov, Top.gg
Author-email: shivaco.osu@gmail.com
License: MIT
Keywords: discord bot server list discordservers serverlist discordbots botlist topgg top.gg
Platform: UNKNOWN
Classifier: Development Status :: 5 - Production/Stable
Classifier: License :: OSI Approved :: MIT License
Classifier: Intended Audience :: Developers
Classifier: Natural Language :: English
Classifier: Operating System :: OS Independent
Classifier: Programming Language :: Python :: 3 :: Only
Classifier: Programming Language :: Python :: 3.6
Classifier: Programming Language :: Python :: 3.7
Classifier: Programming Language :: Python :: 3.8
Classifier: Programming Language :: Python :: 3.9
Classifier: Topic :: Internet
Classifier: Topic :: Software Development :: Libraries
Classifier: Topic :: Software Development :: Libraries :: Python Modules
Classifier: Topic :: Utilities
Requires-Python: >= 3.6
License-File: LICENSE
